xtimetracker/__init__.py
xtimetracker/__main__.py
xtimetracker/autocompletion.py
xtimetracker/backend.py
xtimetracker/cli.py
xtimetracker/cli_utils.py
xtimetracker/config.py
xtimetracker/date_utils.py
xtimetracker/file_utils.py
xtimetracker/frames.py
xtimetracker/timetracker.py
xtimetracker/utils.py
xtimetracker-0.1.1.dist-info/GPL-3.0-or-later.txt
xtimetracker-0.1.1.dist-info/METADATA
xtimetracker-0.1.1.dist-info/MIT.txt
xtimetracker-0.1.1.dist-info/WHEEL
xtimetracker-0.1.1.dist-info/entry_points.txt
xtimetracker-0.1.1.dist-info/top_level.txt
xtimetracker-0.1.1.dist-info/zip-safe
xtimetracker-0.1.1.dist-info/RECORD
