Metadata-Version: 2.1
Name: xtimetracker
Version: 0.1.1
Summary: Simple time tracking from the command line
Home-page: https://github.com/davidag/xtimetracker
Author: David Alfonso
Author-email: developer@davidalfonso.es
License: GPL-3.0-or-later AND MIT
Keywords: time,tracker,project,management
Platform: UNKNOWN
Classifier: Development Status :: 3 - Alpha
Classifier: Programming Language :: Python :: 3
Classifier: Programming Language :: Python :: 3.6
Classifier: Programming Language :: Python :: 3.7
Classifier: Programming Language :: Python :: 3.8
Classifier: License :: OSI Approved :: MIT License
Classifier: License :: OSI Approved :: GNU General Public License v3 or later (GPLv3+)
Classifier: Environment :: Console
Classifier: Operating System :: OS Independent
Classifier: Topic :: Office/Business
Classifier: Topic :: Utilities
Requires-Python: >=3.6
Requires-Dist: click (~=7.1)
Requires-Dist: arrow (~=0.17)
